{
    "categories": [
        {
            "title": "Trợ từ",
            "items": [
                "N1 は N2 です - N1 là N2 (khẳng định)",
                "N1 は N2 じゃありません - N1 không phải N2 (Phủ định)",
                "N1 は N2 ですか - N1 có phải là N2 (Nghi vấn)",
                "N1 と N2 です - N1 và N2",
                "N1 や N2 など です - N1, N2, v.v",
                "N1 の N2 ですか - N2 của N1 (Sở hữu/ chủng loại)",
                "も - cũng (thay cho は)",
                "に - trợ từ chỉ thời gian",
                "を - trợ từ chỉ hành động",
                "へ - trợ từ chỉ hành động di chuyển"
            ]
        },
        {
            "title": "Từ chỉ vị trí",
            "items": [
                "これ・それ・あれ - Cái này/ đó/ kia",
                "こちら・そちら・あちら - Cái này/ đó/ kia (lịch sự)",
                "この・その・あの N - Cái N này/ đó/ kia",
                "ここ・そこ・あこ - Chỗ này/ đó/ kia",
                "どこ – Trường học ở đâu?"
            ]
        },
        {
            "title": "Hỏi địa điểm",
            "items": [
                "学校はどこですか？ – Trường học ở đâu?",
                "会社はどちらですか？ – Công ty ở đâu?",
                "うち / 家はどこですか？ – Nhà bạn ở đâu?"
            ]
        },
        {
            "title": "Hỏi đất nước",
            "items": [
                "お国はどちらですか？ – Nước bạn ở đâu?",
                "ベトナムです。 – Việt Nam."
            ]
        },
        {
            "title": "Hỏi tiền",
            "items": [
                "いくらですか？ – Bao nhiêu tiền?",
                "～円です。 – ~ yên."
            ]
        },
        {
            "title": "Hỏi chủng loại/ xuất xứ/ sở hữu",
            "items": [
                "これは 何の N1   ですか？ – Cái N1 này là (chủng loại) gì?",
                "N2 の (N1) です。 – N1 (chủng loại) N2",
                "",
                "これは どこの N1 ですか？ – Cái N1 này xuất xứ ở đấu?",
                "N2 の (N1) です。 – N1 (xuất xứ ở/ của) N2",
                "",
                "これは 誰の N1 ですか？ – Cái N1 này của ai?",
                "N2 の (N1) です。 – N1 của N2"
            ]
        },
        {
            "title": "Hỏi thời gian",
            "items": [
                "今 何時 ですか？ – Bây giờ là mấy giờ?",
                "～時～分 です – ...giờ...phút",
                "毎朝 / まいあさ – mỗi sáng",
                "毎晩 / まいばん – mỗi tối"
            ]
        },
        {
            "title": "Hỏi từ bằng ngôn ngữ khác",
            "items": [
                "「A」は B語 で 何ですか？ – 'A' bằng tiếng B là gì?"
            ]
        },
        {
            "title": "Chia động từ",
            "items": [
                "V ます – Động từ (khẳng định)",
                "V ません – Động từ (phủ định)"
            ]
        },
        {
            "title": "Gọi món",
            "items": [
                "N を (～つ) ください - Cho tôi gọi (...cái) N"
            ]
        }
    ]
}
